accuralai_rag/__init__.py
accuralai_rag/cache.py
accuralai_rag/chunking.py
accuralai_rag/context.py
accuralai_rag/embeddings.py
accuralai_rag/pipeline.py
accuralai_rag/query.py
accuralai_rag/search.py
accuralai_rag/types.py
accuralai_rag/utils.py
accuralai_rag-0.2.1.dist-info/METADATA
accuralai_rag-0.2.1.dist-info/WHEEL
accuralai_rag-0.2.1.dist-info/licenses/LICENSE
accuralai_rag-0.2.1.dist-info/RECORD
