Metadata-Version: 2.4
Name: accuralai-rag
Version: 0.2.1
Summary: High-performance retrieval augmented generation components for the AccuralAI ecosystem.
Project-URL: homepage, https://accural-ai.web.app/
Project-URL: repository, https://github.com/AccuralAI/AccuralAI
Author: AccuralAI Maintainers
License: Apache-2.0
License-File: LICENSE
Requires-Python: >=3.10
Requires-Dist: accuralai-core
Requires-Dist: numpy>=1.23
Provides-Extra: dev
Requires-Dist: pytest; extra == 'dev'
Requires-Dist: pytest-asyncio; extra == 'dev'
Requires-Dist: pytest-mock; extra == 'dev'
Provides-Extra: faiss
Requires-Dist: faiss-cpu>=1.7.4; extra == 'faiss'
Provides-Extra: redis
Requires-Dist: redis>=5.0; extra == 'redis'
Provides-Extra: torch
Requires-Dist: torch; extra == 'torch'
Provides-Extra: transformers
Requires-Dist: sentence-transformers>=2.3.0; extra == 'transformers'
Requires-Dist: transformers>=4.36; extra == 'transformers'
